slicey.py
slicey-0.1.0.dist-info/LICENSE
slicey-0.1.0.dist-info/METADATA
slicey-0.1.0.dist-info/WHEEL
slicey-0.1.0.dist-info/top_level.txt
slicey-0.1.0.dist-info/RECORD
