Metadata-Version: 2.1
Name: slicey
Version: 0.1.0
Summary: Add Mutating Slices to Python
Home-page: https://github.com/TG-Techie/slicey
Author: TG-Techie (Jonah Y-M)
Author-email: tgtechie01@gmail.com
License: UNKNOWN
Platform: UNKNOWN
Classifier: Programming Language :: Python :: 3
Classifier: License :: OSI Approved :: MIT License
Classifier: Operating System :: OS Independent
Requires-Python: >=3.6
